adotsdot/__init__.py
adotsdot/_nodes.py
adotsdot-0.0.2.dist-info/METADATA
adotsdot-0.0.2.dist-info/WHEEL
adotsdot-0.0.2.dist-info/licenses/LICENSE
adotsdot-0.0.2.dist-info/RECORD
