Metadata-Version: 2.1
Name: adotsdot
Version: 0.0.2
Summary: JSON serializable data comparator library.
Project-URL: Homepage, https://gitlab.com/LightlessNight/adotsdot
Project-URL: Bug Tracker, https://gitlab.com/LightlessNight/adotsdot/-/issues
Author: Lightless Night
License-File: LICENSE
Classifier: Operating System :: OS Independent
Classifier: Programming Language :: Python :: 3
Requires-Python: >=3.6
